tmpserver/__init__.py
tmpserver/tmpserver.py
tmpserver-0.0.2.dist-info/LICENSE
tmpserver-0.0.2.dist-info/METADATA
tmpserver-0.0.2.dist-info/WHEEL
tmpserver-0.0.2.dist-info/entry_points.txt
tmpserver-0.0.2.dist-info/top_level.txt
tmpserver-0.0.2.dist-info/RECORD
