Metadata-Version: 2.1
Name: tmpserver
Version: 0.0.2
Summary: create temporary http server quickily,and show qrcode in terminal
Home-page: https://github.com/xyok/tmpserver.git
Author: xyok
Author-email: xy___ok@163.com
License: MIT
Keywords: http,server,qrcode
Platform: UNKNOWN
Classifier: Programming Language :: Python :: 3
Classifier: Programming Language :: Python :: 2.7
Classifier: License :: OSI Approved :: MIT License
Classifier: Operating System :: OS Independent
Requires-Dist: qrcode
